{
  "_class": "group",
  "booleanOperation": -1,
  "clippingMaskMode": 0,
  "do_objectID": "79C4B986-60C5-43DD-A2FA-2DF34E17DE20",
  "exportOptions": {
    "_class": "exportOptions",
    "exportFormats": [
    ],
    "includedLayerIds": [
    ],
    "layerOptions": 0,
    "shouldTrim": false
  },
  "frame": {
    "_class": "rect",
    "constrainProportions": false,
    "height": 164,
    "width": 188,
    "x": 16,
    "y": 16
  },
  "groupLayout": {
    "_class": "MSImmutableFreeformGroupLayout"
  },
  "hasClickThrough": false,
  "hasClippingMask": false,
  "isFixedToViewport": false,
  "isFlippedHorizontal": false,
  "isFlippedVertical": false,
  "isLocked": false,
  "isVisible": true,
  "layerListExpandedType": 2,
  "layers": [
    {
      "class": "text",
      "id": "76741A07-6EAB-4B5A-9A79-A497A5AA5067"
    },
    {
      "class": "text",
      "id": "D48AD053-EA70-4C48-A124-418C1D7E30EB"
    },
    {
      "class": "text",
      "id": "6C5330D6-244E-4FF7-9ABE-C9CC92389855"
    },
    {
      "class": "text",
      "id": "2F8E443E-77E0-45D0-93FD-CFE4437CB497"
    },
    {
      "class": "text",
      "id": "466AD9C5-11E1-4FE5-8276-E086F68C8EDA"
    },
    {
      "class": "text",
      "id": "9088BFE8-8AE8-4713-99A5-06522BCCC149"
    },
    {
      "class": "text",
      "id": "627136CF-0E8E-497B-967A-7CC06F8D8582"
    }
  ],
  "name": "Group 6",
  "nameIsFixed": false,
  "resizingConstraint": 63,
  "resizingType": 0,
  "rotation": 0,
  "shouldBreakMaskChain": false,
  "style": {
    "_class": "style",
    "blur": {
      "_class": "blur",
      "center": "{0.5, 0.5}",
      "isEnabled": false,
      "motionAngle": 0,
      "radius": 10,
      "saturation": 1,
      "type": 0
    },
    "borderOptions": {
      "_class": "borderOptions",
      "dashPattern": [
      ],
      "isEnabled": true,
      "lineCapStyle": 0,
      "lineJoinStyle": 0
    },
    "borders": [
    ],
    "colorControls": {
      "_class": "colorControls",
      "brightness": 0,
      "contrast": 1,
      "hue": 0,
      "isEnabled": false,
      "saturation": 1
    },
    "contextSettings": {
      "_class": "graphicsContextSettings",
      "blendMode": 0,
      "opacity": 1
    },
    "do_objectID": "94A1F8E0-AEFB-4E5A-8067-F90053513591",
    "endMarkerType": 0,
    "fills": [
    ],
    "innerShadows": [
    ],
    "miterLimit": 10,
    "shadows": [
    ],
    "startMarkerType": 0,
    "windingRule": 1
  }
}